{
  "name": "frontendcore-scss",
  "version": "1.2.5",
  "authors": [
    "Toni Pinel <tonipinel@gmail.com>"
  ],
  "main": "Gruntfile.js",
  "moduleType": [
    "amd"
  ],
  "homepage": "http://www.frontendcore.com",
  "private": true,
  "ignore": [
    "node_modules",
    "bower_components",
    "tests"
  ],
  "_release": "1.2.5",
  "_resolution": {
    "type": "version",
    "tag": "1.2.5",
    "commit": "00712391d133586e862d323db843c07a5b329da4"
  },
  "_source": "https://github.com/tonipinel/frontendcore-scss.git",
  "_target": "1.2.5",
  "_originalSource": "https://github.com/tonipinel/frontendcore-scss.git"
}